font_ocr/__init__.py
font_ocr/font_ocr.py
font_spider_ocr/__init__.py
font_spider_ocr/xi_font_spider_ocr.py
xi_font_spider_ocr/__init__.py
xi_font_spider_ocr/xi_font_spider_ocr.py
font_ocr-1.0.0.dist-info/METADATA
font_ocr-1.0.0.dist-info/WHEEL
font_ocr-1.0.0.dist-info/top_level.txt
font_ocr-1.0.0.dist-info/RECORD
