Metadata-Version: 2.2
Name: font_ocr
Version: 1.0.0
Summary: 使用OCR解决文字反爬
Home-page: https://github.com/Tlyer233/
Author: 明廷盛
Author-email: [email protected]
Keywords: font anti-crawler ocr web-scraping
Classifier: Programming Language :: Python :: 3
Classifier: Development Status :: 5 - Production/Stable
Classifier: Intended Audience :: Developers
Classifier: Topic :: Software Development :: Libraries :: Python Modules
Classifier: License :: OSI Approved :: MIT License
Classifier: Operating System :: OS Independent
Classifier: Programming Language :: Python :: 3.7
Classifier: Programming Language :: Python :: 3.8
Classifier: Programming Language :: Python :: 3.9
Classifier: Programming Language :: Python :: 3.10
Classifier: Programming Language :: Python :: 3.11
Requires-Python: >=3.7
Requires-Dist: fonttools>=4.44.0
Requires-Dist: lxml>=4.9.2
Requires-Dist: loguru>=0.7.0
Requires-Dist: ddddocr>=1.4.9
Requires-Dist: matplotlib>=3.7.1
Dynamic: author
Dynamic: author-email
Dynamic: classifier
Dynamic: description
Dynamic: description-content-type
Dynamic: home-page
Dynamic: keywords
Dynamic: requires-dist
Dynamic: requires-python
Dynamic: summary
